<?xml version="1.0"?>
<!-- The COPYRIGHT file at the top level of this repository contains the full
     copyright notices and license terms. -->
<tree string="Payslip Line">
    <field name="payslip"/>
    <field name="type"/>
    <field name="working_hours"/>
    <field name="worked_hours"/>
    <field name="leave_hours"/>
    <field name="generated_entitled_hours"/>
    <field name="total_hours"/>
    <field name="remaining_hours"/>
    <field name="extra_hours"/>
    <field name="leave_payment_hours"/>
    <field name="amount"/>
</tree>
